apistar_dramatiq/__init__.py
apistar_dramatiq/decorators.py
apistar_dramatiq/injector.py
apistar_dramatiq-0.2.1.dist-info/DESCRIPTION.rst
apistar_dramatiq-0.2.1.dist-info/METADATA
apistar_dramatiq-0.2.1.dist-info/RECORD
apistar_dramatiq-0.2.1.dist-info/WHEEL
apistar_dramatiq-0.2.1.dist-info/metadata.json
apistar_dramatiq-0.2.1.dist-info/top_level.txt
