Metadata-Version: 2.0
Name: apistar-dramatiq
Version: 0.2.1
Summary: Dramatiq integration for API Star.
Home-page: UNKNOWN
Author: UNKNOWN
Author-email: UNKNOWN
License: UNKNOWN
Platform: UNKNOWN
Requires-Dist: apistar (>=0.4)
Requires-Dist: dramatiq (>=1.0)
